LICENSE
MANIFEST.in
README.rst
requirements.txt
setup.py
appcore/__init__.py
appcore/conf.py
appcore/views/__init__.py
appcore/views/decorators.py
appcore/views/errors.py
appcore/views/mixins.py
django_appcore.egg-info/PKG-INFO
django_appcore.egg-info/SOURCES.txt
django_appcore.egg-info/dependency_links.txt
django_appcore.egg-info/not-zip-safe
django_appcore.egg-info/requires.txt
django_appcore.egg-info/top_level.txt
docs/TODO
docs/install.rst
docs/usage.rst