Metadata-Version: 1.1
Name: django-appcore
Version: 0.0.4
Summary: Reusable useful tools for Django 1.5+ application programming.
Home-page: https://github.com/dlancer/django-appcore
Author: dlancer
Author-email: dmdpost@gmail.com
License: BSD
Platform: UNKNOWN
Classifier: Environment :: Web Environment
Classifier: Framework :: Django
Classifier: Intended Audience :: Developers
Classifier: License :: OSI Approved :: BSD License
Classifier: Operating System :: OS Independent
Classifier: Programming Language :: Python
Classifier: Programming Language :: Python :: 2.7
Classifier: Programming Language :: Python :: 3.3
Classifier: Programming Language :: Python :: 3.4
Classifier: Topic :: Internet :: WWW/HTTP
Classifier: Topic :: Internet :: WWW/HTTP :: Dynamic Content
Classifier: Development Status :: 2 - Pre-Alpha
